Modulos/Azure.py
Modulos/Cloud.py
Modulos/GCP.py
Modulos/__init__.py
luisteste-0.1.data/scripts/stone_cli.py
luisteste-0.1.dist-info/METADATA
luisteste-0.1.dist-info/WHEEL
luisteste-0.1.dist-info/top_level.txt
luisteste-0.1.dist-info/RECORD
